guard_agent/__init__.py
guard_agent/buffer.py
guard_agent/client.py
guard_agent/encryption.py
guard_agent/models.py
guard_agent/protocols.py
guard_agent/py.typed
guard_agent/transport.py
guard_agent/utils.py
fastapi_guard_agent-1.1.0.dist-info/LICENSE
fastapi_guard_agent-1.1.0.dist-info/METADATA
fastapi_guard_agent-1.1.0.dist-info/WHEEL
fastapi_guard_agent-1.1.0.dist-info/top_level.txt
fastapi_guard_agent-1.1.0.dist-info/RECORD
