Metadata-Version: 2.1
Name: fastapi-guard-agent
Version: 1.1.0
Summary: Telemetry and monitoring agent for FastAPI Guard security middleware
Author-email: Renzo Franceschini <rennf93@users.noreply.github.com>
License: MIT
Project-URL: Homepage, https://github.com/rennf93/fastapi-guard-agent
Classifier: Development Status :: 3 - Alpha
Classifier: Framework :: FastAPI
Classifier: Intended Audience :: Developers
Classifier: License :: OSI Approved :: MIT License
Classifier: Operating System :: OS Independent
Classifier: Programming Language :: Python :: 3
Classifier: Programming Language :: Python :: 3.10
Classifier: Programming Language :: Python :: 3.11
Classifier: Programming Language :: Python :: 3.12
Classifier: Programming Language :: Python :: 3.13
Classifier: Topic :: Security
Classifier: Topic :: System :: Monitoring
Requires-Python: <3.14,>=3.10
License-File: LICENSE
Requires-Dist: cryptography
Requires-Dist: httpx
Requires-Dist: fastapi
Requires-Dist: fastapi-guard
Requires-Dist: pydantic
Requires-Dist: typing-extensions
Provides-Extra: dev
Requires-Dist: black; extra == "dev"
Requires-Dist: httpx; extra == "dev"
Requires-Dist: mkdocs; extra == "dev"
Requires-Dist: mkdocstrings; extra == "dev"
Requires-Dist: mkdocstrings-python; extra == "dev"
Requires-Dist: mkdocs-material; extra == "dev"
Requires-Dist: mypy; extra == "dev"
Requires-Dist: pre-commit; extra == "dev"
Requires-Dist: psutil; extra == "dev"
Requires-Dist: pymarkdownlnt; extra == "dev"
Requires-Dist: pytest; extra == "dev"
Requires-Dist: pytest-asyncio; extra == "dev"
Requires-Dist: pytest-cov; extra == "dev"
Requires-Dist: pytest-mock; extra == "dev"
Requires-Dist: ruff; extra == "dev"
Requires-Dist: types-psutil; extra == "dev"
Requires-Dist: types-setuptools; extra == "dev"
Provides-Extra: redis
Requires-Dist: redis; extra == "redis"
